MANIFEST.in
README.rst
setup.cfg
setup.py
ckanext/__init__.py
ckanext/harvest/__init__.py
ckanext/harvest/helpers.py
ckanext/harvest/interfaces.py
ckanext/harvest/plugin.py
ckanext/harvest/queue.py
ckanext/harvest/commands/__init__.py
ckanext/harvest/commands/harvester.py
ckanext/harvest/controllers/__init__.py
ckanext/harvest/controllers/dspadmin.py
ckanext/harvest/controllers/organization.py
ckanext/harvest/controllers/view.py
ckanext/harvest/harvesters/__init__.py
ckanext/harvest/harvesters/base.py
ckanext/harvest/harvesters/ckanharvester.py
ckanext/harvest/harvesters/dspckanharvester.py
ckanext/harvest/harvesters/taipeiharvester.py
ckanext/harvest/logic/__init__.py
ckanext/harvest/logic/dictization.py
ckanext/harvest/logic/schema.py
ckanext/harvest/logic/validators.py
ckanext/harvest/logic/action/__init__.py
ckanext/harvest/logic/action/create.py
ckanext/harvest/logic/action/delete.py
ckanext/harvest/logic/action/get.py
ckanext/harvest/logic/action/update.py
ckanext/harvest/logic/auth/__init__.py
ckanext/harvest/logic/auth/create.py
ckanext/harvest/logic/auth/delete.py
ckanext/harvest/logic/auth/get.py
ckanext/harvest/logic/auth/update.py
ckanext/harvest/model/__init__.py
ckanext/harvest/public/ckanext/harvest/style.css
ckanext/harvest/public/ckanext/harvest/images/icons/source_delete.png
ckanext/harvest/public/ckanext/harvest/images/icons/source_edit.png
ckanext/harvest/public/ckanext/harvest/images/icons/source_new.png
ckanext/harvest/public/ckanext/harvest/images/icons/source_refresh.png
ckanext/harvest/public/ckanext/harvest/images/icons/source_view.png
ckanext/harvest/public/ckanext/harvest/javascript/extra_fields.js
ckanext/harvest/public/ckanext/harvest/javascript/resource.config
ckanext/harvest/templates/base.html
ckanext/harvest/templates/header.html
ckanext/harvest/templates/index.html
ckanext/harvest/templates/admin/sync.html
ckanext/harvest/templates/snippets/add_source_button.html
ckanext/harvest/templates/snippets/job_details.html
ckanext_harvest_zh.egg-info/.DS_Store
ckanext_harvest_zh.egg-info/PKG-INFO
ckanext_harvest_zh.egg-info/SOURCES.txt
ckanext_harvest_zh.egg-info/dependency_links.txt
ckanext_harvest_zh.egg-info/entry_points.txt
ckanext_harvest_zh.egg-info/not-zip-safe
ckanext_harvest_zh.egg-info/top_level.txt