Metadata-Version: 1.0
Name: ckanext-harvest-zh
Version: 0.3.2
Summary: An improved harvest package to collect Chinese language data sets for CKAN. 
Home-page: https://dsp.im
Author: CKAN, Bing-Si Ni, Bo-Han Wu
Author-email: UNKNOWN
License: MIT
Keywords: ckan,Linked-data,harvest
Platform: UNKNOWN
